kh2lib/__init__.py
kh2lib/ddd.py
kh2lib/kh2fmtoolkit.py
kh2lib/kh2lib.py
kh2lib/memoryparser.py
kh2lib/openKH.py
kh2lib/pnachmaker.py
kh2lib/utils.py
kh2lib/data/character_records.yaml
kh2lib/data/characters
kh2lib/data/inventory
kh2lib/data/objlist.json
kh2lib/data/tt01.spawnscript
kh2lib/data/worlds.json
kh2lib-0.2.dist-info/METADATA
kh2lib-0.2.dist-info/RECORD
kh2lib-0.2.dist-info/WHEEL
kh2lib-0.2.dist-info/top_level.txt
