Metadata-Version: 2.1
Name: kh2lib
Version: 0.2
Summary: UNKNOWN
Home-page: https://github.com/snelson3/kh2lib
Author: Thundrio
Author-email: thundrio@yahoo.com
Maintainer-email: thundrio@yahoo.com
License: MIT
Platform: any
Classifier: Intended Audience :: Developers
Classifier: Operating System :: OS Independent
Classifier: Programming Language :: Python :: 3
Requires-Dist: PyYAML
